torchPDLP/__init__.py
torchPDLP/enhancements.py
torchPDLP/helpers.py
torchPDLP/main.py
torchPDLP/primal_dual_hybrid_gradient.py
torchPDLP/primal_dual_hybrid_gradient_step.py
torchPDLP/solve.py
torchPDLP/spectral_casting.py
torchPDLP/util.py
torchpdlp-0.1.2.dist-info/licenses/LICENSE
torchpdlp-0.1.2.dist-info/METADATA
torchpdlp-0.1.2.dist-info/WHEEL
torchpdlp-0.1.2.dist-info/entry_points.txt
torchpdlp-0.1.2.dist-info/top_level.txt
torchpdlp-0.1.2.dist-info/RECORD
