Metadata-Version: 2.4
Name: torchPDLP
Version: 0.1.2
Summary: Uses a PyTorch-implemented restarted PDHG algorithm with enhancements to solve primal-dual linear programs.
Author: Xiyan Hu, Titus Parker, Connor Phillips, Yifa Yu
License: MIT
Project-URL: Homepage, https://github.com/SimplySnap/torchPDLP
Keywords: optimization,primal-dual,linear programming,PDHG,torch
Requires-Python: >=3.6
License-File: LICENSE
Requires-Dist: numpy
Requires-Dist: torch
Requires-Dist: pandas
Dynamic: license-file
